github_scraper/__init__.py
github_scraper/config.py
github_scraper/owner.py
github_scraper/utils.py
github_scraper-0.1.1.dist-info/LICENSE
github_scraper-0.1.1.dist-info/METADATA
github_scraper-0.1.1.dist-info/WHEEL
github_scraper-0.1.1.dist-info/top_level.txt
github_scraper-0.1.1.dist-info/RECORD
