Metadata-Version: 2.1
Name: github-scraper
Version: 0.1.1
Summary: Simple python tool for download source code from GitHub
Home-page: https://github.com/basedrhys/github-scraper
Author: basedrhys
Author-email: rhys.compton@gmail.com
License: MIT
Platform: UNKNOWN
